canonical-amis
canonical_amis.py
setup.py
canonical_amis.egg-info/PKG-INFO
canonical_amis.egg-info/SOURCES.txt
canonical_amis.egg-info/dependency_links.txt
canonical_amis.egg-info/requires.txt
canonical_amis.egg-info/top_level.txt