Metadata-Version: 1.1
Name: canonical-amis
Version: 0.1.0-beta.3
Summary: Find AWS EC2 AMIs for Canonical Ubuntu images
Home-page: https://github.com/divitu/canonical-amis
Author: Colin von Heuring
Author-email: colin@von.heuri.ng
License: GNU General Public License
Download-URL: https://pypi.python.org/packages/source/c/canonical-amis/canonical-amis-0.1.0-beta.3.tar.gz
Platform: any
Classifier: Development Status :: 4 - Beta
Classifier: Intended Audience :: System Administrators
Classifier: License :: OSI Approved :: GNU General Public License v2 or later (GPLv2+)
Classifier: Programming Language :: Python
Classifier: Topic :: Software Development :: Libraries :: Python Modules
Classifier: Operating System :: OS Independent
